exclip/__init__.py
exclip/explanation.py
exclip/tokenization.py
exclip-1.1.dist-info/licenses/LICENSE
exclip-1.1.dist-info/METADATA
exclip-1.1.dist-info/WHEEL
exclip-1.1.dist-info/top_level.txt
exclip-1.1.dist-info/RECORD
