Metadata-Version: 2.4
Name: exclip
Version: 1.1
Summary: A wrapper package for CLIP, providing explanations for how the model compares images and captions.
Author-email: Lucas Moeller <lucasmoeller@icloud.com>, Pascal Tilli <pascal.tilli@ims.uni-stuttgart>
Project-URL: Homepage, https://github.com/lucasmllr/exCLIP
Project-URL: Bug Tracker, https://github.com/lucasmllr/exCLIP/issues
Classifier: Programming Language :: Python :: 3
Classifier: License :: OSI Approved :: MIT License
Classifier: Operating System :: OS Independent
Requires-Python: >=3.11
License-File: LICENSE
Requires-Dist: numpy
Requires-Dist: torch
Requires-Dist: torchvision
Requires-Dist: tqdm
Requires-Dist: matplotlib
Requires-Dist: pillow
Requires-Dist: opencv-python
Requires-Dist: ftfy
Requires-Dist: regex
Requires-Dist: ipykernel
Requires-Dist: open_clip_torch
Dynamic: license-file
